README.md
diqu/__entrypoint__.py
diqu/__init__.py
diqu/__main__.py
diqu/alerts/__init__.py
diqu/alerts/factory.py
diqu/alerts/jira.py
diqu/alerts/slack.py
diqu/cli/__init__.py
diqu/cli/common.py
diqu/cli/main.py
diqu/packages/__init__.py
diqu/packages/csv.py
diqu/packages/dq_tools.py
diqu/packages/factory.py
diqu/packages/include/dq_tools__get_test_results.sql
diqu/packages/query.py
diqu/sources/__init__.py
diqu/sources/base.py
diqu/sources/csv.py
diqu/sources/factory.py
diqu/sources/snowflake.py
diqu/tasks/__init__.py
diqu/tasks/alert.py
diqu/tasks/base.py
diqu/utils/__init__.py
diqu/utils/exception.py
diqu/utils/log.py
diqu/utils/meta.py
diqu/utils/module.py
diqu/utils/tracking.py
diqu/utils/yml.py
diqu-0.2.0.dist-info/LICENSE
diqu-0.2.0.dist-info/METADATA
diqu-0.2.0.dist-info/WHEEL
diqu-0.2.0.dist-info/entry_points.txt
diqu-0.2.0.dist-info/RECORD
