Metadata-Version: 2.1
Name: diqu
Version: 0.2.0
Summary: Data Quality CLI for the Auto-Alerts
Home-page: https://infinitelambda.com
License: Apache-2.0
Keywords: packaging,poetry,data-quality,alert,notification,collaboration,agility,flake8,markdown,lint
Author: Infinite Lambda
Author-email: contact@infinitelambda.com
Requires-Python: >=3.9,<3.13
Classifier: Environment :: Console
Classifier: License :: OSI Approved :: Apache Software License
Classifier: Operating System :: OS Independent
Classifier: Programming Language :: Python :: 3
Classifier: Programming Language :: Python :: 3.9
Classifier: Programming Language :: Python :: 3.10
Classifier: Programming Language :: Python :: 3.11
Classifier: Programming Language :: Python :: 3.12
Classifier: Topic :: Software Development :: Documentation
Classifier: Topic :: Software Development :: Libraries :: Python Modules
Classifier: Topic :: Software Development :: Quality Assurance
Requires-Dist: jira (>=3.5.2,<4.0.0)
Requires-Dist: numpy (<2.0)
Requires-Dist: pandas (>=1.0,<2.1)
Requires-Dist: pyyaml (>=6.0.1,<7.0.0)
Requires-Dist: rich-click (>=1.7.0,<2.0.0)
Requires-Dist: slack-sdk (>=3.23.0,<4.0.0)
Requires-Dist: snowplow-tracker (>=1.0.1,<2.0.0)
Project-URL: Documentation, https://diqu.iflambda.com/latest/
Project-URL: Repository, https://github.com/infinitelambda/diqu
